{"nodes": [{"id": "read", "label": "read.py", "file_type": "code", "source_file": "app/schemas/chat/read.py", "source_location": "L1"}, {"id": "read_chatread", "label": "ChatRead", "file_type": "code", "source_file": "app/schemas/chat/read.py", "source_location": "L11"}, {"id": "chatbase", "label": "ChatBase", "file_type": "code", "source_file": "", "source_location": ""}, {"id": "readbase", "label": "ReadBase", "file_type": "code", "source_file": "", "source_location": ""}, {"id": "read_chatmessageread", "label": "ChatMessageRead", "file_type": "code", "source_file": "app/schemas/chat/read.py", "source_location": "L19"}], "edges": [{"source": "read", "target": "datetime", "relation": "imports_from", "confidence": "EXTRACTED", "source_file": "app/schemas/chat/read.py", "source_location": "L1", "weight": 1.0}, {"source": "read", "target": "app_enums", "relation": "imports_from", "confidence": "EXTRACTED", "source_file": "app/schemas/chat/read.py", "source_location": "L3", "weight": 1.0}, {"source": "read", "target": "app_schemas_base", "relation": "imports_from", "confidence": "EXTRACTED", "source_file": "app/schemas/chat/read.py", "source_location": "L4", "weight": 1.0}, {"source": "read", "target": "app_schemas_item_preview", "relation": "imports_from", "confidence": "EXTRACTED", "source_file": "app/schemas/chat/read.py", "source_location": "L5", "weight": 1.0}, {"source": "read", "target": "app_schemas_user_preview", "relation": "imports_from", "confidence": "EXTRACTED", "source_file": "app/schemas/chat/read.py", "source_location": "L6", "weight": 1.0}, {"source": "read", "target": "base", "relation": "imports_from", "confidence": "EXTRACTED", "source_file": "app/schemas/chat/read.py", "source_location": "L8", "weight": 1.0}, {"source": "read", "target": "read_chatread", "relation": "contains", "confidence": "EXTRACTED", "source_file": "app/schemas/chat/read.py", "source_location": "L11", "weight": 1.0}, {"source": "read_chatread", "target": "chatbase", "relation": "inherits", "confidence": "EXTRACTED", "source_file": "app/schemas/chat/read.py", "source_location": "L11", "weight": 1.0}, {"source": "read_chatread", "target": "readbase", "relation": "inherits", "confidence": "EXTRACTED", "source_file": "app/schemas/chat/read.py", "source_location": "L11", "weight": 1.0}, {"source": "read", "target": "read_chatmessageread", "relation": "contains", "confidence": "EXTRACTED", "source_file": "app/schemas/chat/read.py", "source_location": "L19", "weight": 1.0}, {"source": "read_chatmessageread", "target": "chatbase", "relation": "inherits", "confidence": "EXTRACTED", "source_file": "app/schemas/chat/read.py", "source_location": "L19", "weight": 1.0}, {"source": "read_chatmessageread", "target": "readbase", "relation": "inherits", "confidence": "EXTRACTED", "source_file": "app/schemas/chat/read.py", "source_location": "L19", "weight": 1.0}]}